[
  {
    "Name": "House",
    "power": 0,
    "sellPrice": 0,
    "healthRepairInterval": 0,
    "repairCostInterval": 0,
    "key": "House",
    "faction_DONTCHANGETHIS": "Neutral_Player",
    "Health": 500,
    "MinAttackDamage": 15,
    "MaxAttackDamage": 15,
    "AttackSpeed": 3,
    "AttackSpread": 0,
    "AttackRate": 0.5,
    "AttackRange": 0,
    "detectionRange": 0.6,
    "FogDiscoveryOuter": 1.35,
    "prodCost": 0,
    "prodTimeCost": 0,
    "AttackDamageType": "Normal",
    "ArmorClass": "HyperHeavy"
  },
  {
    "Name": "Guard Tower",
    "power": -20,
    "sellPrice": 360,
    "healthRepairInterval": 3,
    "repairCostInterval": 3,
    "key": "Guard Tower",
    "faction_DONTCHANGETHIS": "Empire_Ascending_Order",
    "Health": 600,
    "MinAttackDamage": 15,
    "MaxAttackDamage": 30,
    "AttackSpeed": 3,
    "AttackSpread": 0,
    "AttackRate": 0.5,
    "AttackRange": 1.2,
    "detectionRange": 1.5,
    "FogDiscoveryOuter": 1.85,
    "prodCost": 600,
    "prodTimeCost": 200,
    "AttackDamageType": "Bullet",
    "ArmorClass": "HyperHeavy"
  },
  {
    "Name": "Guard Tower",
    "power": -20,
    "sellPrice": 360,
    "healthRepairInterval": 3,
    "repairCostInterval": 3,
    "key": "Guard Tower",
    "faction_DONTCHANGETHIS": "West_World_Alliance",
    "Health": 600,
    "MinAttackDamage": 15,
    "MaxAttackDamage": 30,
    "AttackSpeed": 3,
    "AttackSpread": 0,
    "AttackRate": 0.5,
    "AttackRange": 1.2,
    "detectionRange": 1.5,
    "FogDiscoveryOuter": 1.85,
    "prodCost": 600,
    "prodTimeCost": 200,
    "AttackDamageType": "Bullet",
    "ArmorClass": "HyperHeavy"
  },
  {
    "Name": "Wired Fence",
    "power": 0,
    "sellPrice": 30,
    "healthRepairInterval": 10,
    "repairCostInterval": 50,
    "key": "Wired Fence",
    "faction_DONTCHANGETHIS": "Empire_Ascending_Order",
    "Health": 10,
    "MinAttackDamage": 15,
    "MaxAttackDamage": 15,
    "AttackSpeed": 3,
    "AttackSpread": 0,
    "AttackRate": 0.5,
    "AttackRange": 0,
    "detectionRange": 0,
    "FogDiscoveryOuter": 0.1,
    "prodCost": 50,
    "prodTimeCost": 1,
    "AttackDamageType": "Normal",
    "ArmorClass": "HyperHeavy"
  },
  {
    "Name": "Wired Fence",
    "power": 0,
    "sellPrice": 30,
    "healthRepairInterval": 10,
    "repairCostInterval": 50,
    "key": "Wired Fence",
    "faction_DONTCHANGETHIS": "West_World_Alliance",
    "Health": 10,
    "MinAttackDamage": 15,
    "MaxAttackDamage": 15,
    "AttackSpeed": 3,
    "AttackSpread": 0,
    "AttackRate": 0.5,
    "AttackRange": 0,
    "detectionRange": 0,
    "FogDiscoveryOuter": 0.1,
    "prodCost": 50,
    "prodTimeCost": 1,
    "AttackDamageType": "Normal",
    "ArmorClass": "HyperHeavy"
  },
  {
    "Name": "Refinery",
    "power": -75,
    "sellPrice": 1197,
    "healthRepairInterval": 3.16,
    "repairCostInterval": 7,
    "key": "Refinery",
    "faction_DONTCHANGETHIS": "Empire_Ascending_Order",
    "Health": 900,
    "MinAttackDamage": 15,
    "MaxAttackDamage": 15,
    "AttackSpeed": 3,
    "AttackSpread": 0,
    "AttackRate": 0.5,
    "AttackRange": 0,
    "detectionRange": 0.6,
    "FogDiscoveryOuter": 1.35,
    "prodCost": 1995,
    "prodTimeCost": 285,
    "AttackDamageType": "Normal",
    "ArmorClass": "HyperHeavy"
  },
  {
    "Name": "Refinery",
    "power": -75,
    "sellPrice": 1197,
    "healthRepairInterval": 3.16,
    "repairCostInterval": 7,
    "key": "Refinery",
    "faction_DONTCHANGETHIS": "West_World_Alliance",
    "Health": 900,
    "MinAttackDamage": 15,
    "MaxAttackDamage": 15,
    "AttackSpeed": 3,
    "AttackSpread": 0,
    "AttackRate": 0.5,
    "AttackRange": 0,
    "detectionRange": 0.6,
    "FogDiscoveryOuter": 1.35,
    "prodCost": 1995,
    "prodTimeCost": 285,
    "AttackDamageType": "Normal",
    "ArmorClass": "HyperHeavy"
  },
  {
    "Name": "Well",
    "power": 0,
    "sellPrice": 0,
    "healthRepairInterval": 0,
    "repairCostInterval": 0,
    "key": "Well",
    "faction_DONTCHANGETHIS": "Neutral_Player",
    "Health": 100,
    "MinAttackDamage": 15,
    "MaxAttackDamage": 15,
    "AttackSpeed": 3,
    "AttackSpread": 0,
    "AttackRate": 0.5,
    "AttackRange": 0,
    "detectionRange": 0.8625,
    "FogDiscoveryOuter": 1.35,
    "prodCost": 0,
    "prodTimeCost": 0,
    "AttackDamageType": "Normal",
    "ArmorClass": "HyperHeavy"
  },
  {
    "Name": "Church",
    "power": 0,
    "sellPrice": 0,
    "healthRepairInterval": 0,
    "repairCostInterval": 0,
    "key": "Church",
    "faction_DONTCHANGETHIS": "Neutral_Player",
    "Health": 2000,
    "MinAttackDamage": 15,
    "MaxAttackDamage": 15,
    "AttackSpeed": 3,
    "AttackSpread": 0,
    "AttackRate": 0.5,
    "AttackRange": 0,
    "detectionRange": 0.6,
    "FogDiscoveryOuter": 1.35,
    "prodCost": 0,
    "prodTimeCost": 0,
    "AttackDamageType": "Normal",
    "ArmorClass": "HyperHeavy"
  },
  {
    "Name": "Vehicle Factory",
    "power": -75,
    "sellPrice": 1200,
    "healthRepairInterval": 2.5,
    "repairCostInterval": 5,
    "key": "Vehicle Factory",
    "faction_DONTCHANGETHIS": "Empire_Ascending_Order",
    "Health": 1000,
    "MinAttackDamage": 15,
    "MaxAttackDamage": 15,
    "AttackSpeed": 3,
    "AttackSpread": 0,
    "AttackRate": 0.5,
    "AttackRange": 0,
    "detectionRange": 0.6,
    "FogDiscoveryOuter": 1.35,
    "prodCost": 2000,
    "prodTimeCost": 400,
    "AttackDamageType": "Normal",
    "ArmorClass": "HyperHeavy"
  },
  {
    "Name": "Vehicle Factory",
    "power": -75,
    "sellPrice": 1200,
    "healthRepairInterval": 2.5,
    "repairCostInterval": 5,
    "key": "Vehicle Factory",
    "faction_DONTCHANGETHIS": "West_World_Alliance",
    "Health": 1000,
    "MinAttackDamage": 15,
    "MaxAttackDamage": 15,
    "AttackSpeed": 3,
    "AttackSpread": 0,
    "AttackRate": 0.5,
    "AttackRange": 0,
    "detectionRange": 0.6,
    "FogDiscoveryOuter": 1.35,
    "prodCost": 2000,
    "prodTimeCost": 400,
    "AttackDamageType": "Normal",
    "ArmorClass": "HyperHeavy"
  },
  {
    "Name": "Command Center (CC)",
    "power": 100,
    "sellPrice": 1500,
    "healthRepairInterval": 120,
    "repairCostInterval": 100,
    "key": "Command Center (CC)",
    "faction_DONTCHANGETHIS": "Empire_Ascending_Order",
    "Health": 3000,
    "MinAttackDamage": 15,
    "MaxAttackDamage": 15,
    "AttackSpeed": 3,
    "AttackSpread": 0,
    "AttackRate": 0.5,
    "AttackRange": 0,
    "detectionRange": 0.6,
    "FogDiscoveryOuter": 1.35,
    "prodCost": 2500,
    "prodTimeCost": 25,
    "AttackDamageType": "Normal",
    "ArmorClass": "HyperHeavy"
  },
  {
    "Name": "Command Center (CC)",
    "power": 100,
    "sellPrice": 1440,
    "healthRepairInterval": 100,
    "repairCostInterval": 80,
    "key": "Command Center (CC)",
    "faction_DONTCHANGETHIS": "West_World_Alliance",
    "Health": 3000,
    "MinAttackDamage": 15,
    "MaxAttackDamage": 15,
    "AttackSpeed": 3,
    "AttackSpread": 0,
    "AttackRate": 0.5,
    "AttackRange": 0,
    "detectionRange": 0.6,
    "FogDiscoveryOuter": 1.35,
    "prodCost": 2400,
    "prodTimeCost": 30,
    "AttackDamageType": "Normal",
    "ArmorClass": "HyperHeavy"
  },
  {
    "Name": "Power Plant",
    "power": 150,
    "sellPrice": 192,
    "healthRepairInterval": 3.75,
    "repairCostInterval": 2,
    "key": "Power Plant",
    "faction_DONTCHANGETHIS": "Empire_Ascending_Order",
    "Health": 600,
    "MinAttackDamage": 15,
    "MaxAttackDamage": 15,
    "AttackSpeed": 3,
    "AttackSpread": 0,
    "AttackRate": 0.5,
    "AttackRange": 0,
    "detectionRange": 0.6,
    "FogDiscoveryOuter": 1.35,
    "prodCost": 320,
    "prodTimeCost": 160,
    "AttackDamageType": "Normal",
    "ArmorClass": "HyperHeavy"
  },
  {
    "Name": "Power Plant",
    "power": 150,
    "sellPrice": 192,
    "healthRepairInterval": 3.75,
    "repairCostInterval": 2,
    "key": "Power Plant",
    "faction_DONTCHANGETHIS": "West_World_Alliance",
    "Health": 600,
    "MinAttackDamage": 15,
    "MaxAttackDamage": 15,
    "AttackSpeed": 3,
    "AttackSpread": 0,
    "AttackRate": 0.5,
    "AttackRange": 0,
    "detectionRange": 0.6,
    "FogDiscoveryOuter": 1.35,
    "prodCost": 320,
    "prodTimeCost": 160,
    "AttackDamageType": "Normal",
    "ArmorClass": "HyperHeavy"
  },
  {
    "Name": "Radar",
    "power": -100,
    "sellPrice": 600,
    "healthRepairInterval": 4,
    "repairCostInterval": 4,
    "key": "Radar",
    "faction_DONTCHANGETHIS": "Empire_Ascending_Order",
    "Health": 1000,
    "MinAttackDamage": 15,
    "MaxAttackDamage": 15,
    "AttackSpeed": 3,
    "AttackSpread": 0,
    "AttackRate": 0.5,
    "AttackRange": 0,
    "detectionRange": 0.6,
    "FogDiscoveryOuter": 1.35,
    "prodCost": 1000,
    "prodTimeCost": 250,
    "AttackDamageType": "Normal",
    "ArmorClass": "HyperHeavy"
  },
  {
    "Name": "Radar",
    "power": -100,
    "sellPrice": 600,
    "healthRepairInterval": 4,
    "repairCostInterval": 4,
    "key": "Radar",
    "faction_DONTCHANGETHIS": "West_World_Alliance",
    "Health": 1000,
    "MinAttackDamage": 15,
    "MaxAttackDamage": 15,
    "AttackSpeed": 3,
    "AttackSpread": 0,
    "AttackRate": 0.5,
    "AttackRange": 0,
    "detectionRange": 0.6,
    "FogDiscoveryOuter": 1.35,
    "prodCost": 1000,
    "prodTimeCost": 250,
    "AttackDamageType": "Normal",
    "ArmorClass": "HyperHeavy"
  },
  {
    "Name": "Barracks",
    "power": -50,
    "sellPrice": 180,
    "healthRepairInterval": 5.33,
    "repairCostInterval": 2,
    "key": "Barracks",
    "faction_DONTCHANGETHIS": "Empire_Ascending_Order",
    "Health": 800,
    "MinAttackDamage": 15,
    "MaxAttackDamage": 15,
    "AttackSpeed": 3,
    "AttackSpread": 0,
    "AttackRate": 0.5,
    "AttackRange": 0,
    "detectionRange": 0.6,
    "FogDiscoveryOuter": 1.35,
    "prodCost": 300,
    "prodTimeCost": 150,
    "AttackDamageType": "Normal",
    "ArmorClass": "HyperHeavy"
  },
  {
    "Name": "Barracks",
    "power": -50,
    "sellPrice": 180,
    "healthRepairInterval": 5.33,
    "repairCostInterval": 2,
    "key": "Barracks",
    "faction_DONTCHANGETHIS": "West_World_Alliance",
    "Health": 800,
    "MinAttackDamage": 15,
    "MaxAttackDamage": 15,
    "AttackSpeed": 3,
    "AttackSpread": 0,
    "AttackRate": 0.5,
    "AttackRange": 0,
    "detectionRange": 0.6,
    "FogDiscoveryOuter": 1.35,
    "prodCost": 300,
    "prodTimeCost": 150,
    "AttackDamageType": "Normal",
    "ArmorClass": "HyperHeavy"
  },
  {
    "Name": "Barrel",
    "power": 0,
    "sellPrice": 0,
    "healthRepairInterval": 0,
    "repairCostInterval": 0,
    "key": "Barrel",
    "faction_DONTCHANGETHIS": "Neutral_Player",
    "Health": 20,
    "MinAttackDamage": 15,
    "MaxAttackDamage": 15,
    "AttackSpeed": 3,
    "AttackSpread": 0,
    "AttackRate": 0.5,
    "AttackRange": 0,
    "detectionRange": 0.6,
    "FogDiscoveryOuter": 1.35,
    "prodCost": 0,
    "prodTimeCost": 0,
    "AttackDamageType": "Normal",
    "ArmorClass": "HyperHeavy"
  },
  {
    "Name": "Bridge",
    "power": 0,
    "sellPrice": 0,
    "healthRepairInterval": 0,
    "repairCostInterval": 0,
    "key": "Bridge",
    "faction_DONTCHANGETHIS": "Neutral_Player",
    "Health": 5000,
    "MinAttackDamage": 15,
    "MaxAttackDamage": 15,
    "AttackSpeed": 3,
    "AttackSpread": 0,
    "AttackRate": 0.5,
    "AttackRange": 0,
    "detectionRange": 0.6,
    "FogDiscoveryOuter": 1.35,
    "prodCost": 0,
    "prodTimeCost": 0,
    "AttackDamageType": "Normal",
    "ArmorClass": "Bridge"
  },
  {
    "Name": "Sandbag",
    "power": 0,
    "sellPrice": 30,
    "healthRepairInterval": 10,
    "repairCostInterval": 50,
    "key": "Sandbag",
    "faction_DONTCHANGETHIS": "Empire_Ascending_Order",
    "Health": 10,
    "MinAttackDamage": 15,
    "MaxAttackDamage": 15,
    "AttackSpeed": 3,
    "AttackSpread": 0,
    "AttackRate": 0.5,
    "AttackRange": 0,
    "detectionRange": 0,
    "FogDiscoveryOuter": 0.1,
    "prodCost": 50,
    "prodTimeCost": 1,
    "AttackDamageType": "Normal",
    "ArmorClass": "HyperHeavy"
  },
  {
    "Name": "Sandbag",
    "power": 0,
    "sellPrice": 30,
    "healthRepairInterval": 10,
    "repairCostInterval": 50,
    "key": "Sandbag",
    "faction_DONTCHANGETHIS": "West_World_Alliance",
    "Health": 10,
    "MinAttackDamage": 15,
    "MaxAttackDamage": 15,
    "AttackSpeed": 3,
    "AttackSpread": 0,
    "AttackRate": 0.5,
    "AttackRange": 0,
    "detectionRange": 0,
    "FogDiscoveryOuter": 0.1,
    "prodCost": 50,
    "prodTimeCost": 1,
    "AttackDamageType": "Normal",
    "ArmorClass": "HyperHeavy"
  },
  {
    "Name": "Trolley",
    "power": 0,
    "sellPrice": 0,
    "healthRepairInterval": 0,
    "repairCostInterval": 0,
    "key": "Trolley",
    "faction_DONTCHANGETHIS": "Neutral_Player",
    "Health": 100,
    "MinAttackDamage": 15,
    "MaxAttackDamage": 15,
    "AttackSpeed": 3,
    "AttackSpread": 0,
    "AttackRate": 0.5,
    "AttackRange": 0,
    "detectionRange": 0.8625,
    "FogDiscoveryOuter": 1.35,
    "prodCost": 0,
    "prodTimeCost": 0,
    "AttackDamageType": "Normal",
    "ArmorClass": "Medium"
  },
  {
    "Name": "Anti-Aircraft Tower",
    "power": -50,
    "sellPrice": 360,
    "healthRepairInterval": 2,
    "repairCostInterval": 3,
    "key": "Anti-Aircraft Tower",
    "faction_DONTCHANGETHIS": "Empire_Ascending_Order",
    "Health": 400,
    "MinAttackDamage": 300,
    "MaxAttackDamage": 350,
    "AttackSpeed": 3,
    "AttackSpread": 0,
    "AttackRate": 1.5,
    "AttackRange": 2,
    "detectionRange": 2.2,
    "FogDiscoveryOuter": 2.3,
    "prodCost": 600,
    "prodTimeCost": 200,
    "AttackDamageType": "Explosion",
    "ArmorClass": "HyperHeavy"
  },
  {
    "Name": "Anti-Aircraft Tower",
    "power": -50,
    "sellPrice": 360,
    "healthRepairInterval": 2,
    "repairCostInterval": 3,
    "key": "Anti-Aircraft Tower",
    "faction_DONTCHANGETHIS": "West_World_Alliance",
    "Health": 400,
    "MinAttackDamage": 300,
    "MaxAttackDamage": 350,
    "AttackSpeed": 3,
    "AttackSpread": 0,
    "AttackRate": 1.5,
    "AttackRange": 2,
    "detectionRange": 2.2,
    "FogDiscoveryOuter": 2.3,
    "prodCost": 600,
    "prodTimeCost": 200,
    "AttackDamageType": "Explosion",
    "ArmorClass": "HyperHeavy"
  },
  {
    "Name": "Flamethrower Tower",
    "power": -60,
    "sellPrice": 360,
    "healthRepairInterval": 3,
    "repairCostInterval": 3,
    "key": "Flamethrower Tower",
    "faction_DONTCHANGETHIS": "Empire_Ascending_Order",
    "Health": 600,
    "MinAttackDamage": 10,
    "MaxAttackDamage": 20,
    "AttackSpeed": 0.3,
    "AttackSpread": 0.13,
    "AttackRate": 0.1,
    "AttackRange": 0.9,
    "detectionRange": 1,
    "FogDiscoveryOuter": 1.35,
    "prodCost": 600,
    "prodTimeCost": 200,
    "AttackDamageType": "Fire",
    "ArmorClass": "HyperHeavy"
  },
  {
    "Name": "Flamethrower Tower",
    "power": -60,
    "sellPrice": 360,
    "healthRepairInterval": 3,
    "repairCostInterval": 3,
    "key": "Flamethrower Tower",
    "faction_DONTCHANGETHIS": "West_World_Alliance",
    "Health": 600,
    "MinAttackDamage": 10,
    "MaxAttackDamage": 20,
    "AttackSpeed": 0.3,
    "AttackSpread": 0.13,
    "AttackRate": 0.1,
    "AttackRange": 0.9,
    "detectionRange": 1,
    "FogDiscoveryOuter": 1.35,
    "prodCost": 600,
    "prodTimeCost": 200,
    "AttackDamageType": "Fire",
    "ArmorClass": "HyperHeavy"
  },
  {
    "Name": "Heavy Barricade",
    "power": 0,
    "sellPrice": 30,
    "healthRepairInterval": 100,
    "repairCostInterval": 50,
    "key": "Heavy Barricade",
    "faction_DONTCHANGETHIS": "Empire_Ascending_Order",
    "Health": 100,
    "MinAttackDamage": 15,
    "MaxAttackDamage": 15,
    "AttackSpeed": 3,
    "AttackSpread": 0,
    "AttackRate": 0.5,
    "AttackRange": 0,
    "detectionRange": 0,
    "FogDiscoveryOuter": 0.1,
    "prodCost": 50,
    "prodTimeCost": 1,
    "AttackDamageType": "Normal",
    "ArmorClass": "HyperHeavy"
  },
  {
    "Name": "Heavy Barricade",
    "power": 0,
    "sellPrice": 30,
    "healthRepairInterval": 100,
    "repairCostInterval": 50,
    "key": "Heavy Barricade",
    "faction_DONTCHANGETHIS": "West_World_Alliance",
    "Health": 100,
    "MinAttackDamage": 15,
    "MaxAttackDamage": 15,
    "AttackSpeed": 3,
    "AttackSpread": 0,
    "AttackRate": 0.5,
    "AttackRange": 0,
    "detectionRange": 0,
    "FogDiscoveryOuter": 0.1,
    "prodCost": 50,
    "prodTimeCost": 1,
    "AttackDamageType": "Normal",
    "ArmorClass": "HyperHeavy"
  },
  {
    "Name": "Silo",
    "power": 0,
    "sellPrice": 90,
    "healthRepairInterval": 2,
    "repairCostInterval": 1,
    "key": "Silo",
    "faction_DONTCHANGETHIS": "Empire_Ascending_Order",
    "Health": 300,
    "MinAttackDamage": 15,
    "MaxAttackDamage": 15,
    "AttackSpeed": 3,
    "AttackSpread": 0,
    "AttackRate": 0.5,
    "AttackRange": 0,
    "detectionRange": 0.8625,
    "FogDiscoveryOuter": 1.35,
    "prodCost": 150,
    "prodTimeCost": 150,
    "AttackDamageType": "Normal",
    "ArmorClass": "HyperHeavy"
  },
  {
    "Name": "Silo",
    "power": 0,
    "sellPrice": 90,
    "healthRepairInterval": 2,
    "repairCostInterval": 1,
    "key": "Silo",
    "faction_DONTCHANGETHIS": "West_World_Alliance",
    "Health": 300,
    "MinAttackDamage": 15,
    "MaxAttackDamage": 15,
    "AttackSpeed": 3,
    "AttackSpread": 0,
    "AttackRate": 0.5,
    "AttackRange": 0,
    "detectionRange": 0.8625,
    "FogDiscoveryOuter": 1.35,
    "prodCost": 150,
    "prodTimeCost": 150,
    "AttackDamageType": "Normal",
    "ArmorClass": "HyperHeavy"
  },
  {
    "Name": "Cannon Tower",
    "power": -40,
    "sellPrice": 360,
    "healthRepairInterval": 3,
    "repairCostInterval": 3,
    "key": "Cannon Tower",
    "faction_DONTCHANGETHIS": "Empire_Ascending_Order",
    "Health": 600,
    "MinAttackDamage": 50,
    "MaxAttackDamage": 50,
    "AttackSpeed": 3,
    "AttackSpread": 0,
    "AttackRate": 3,
    "AttackRange": 1.6,
    "detectionRange": 1.7,
    "FogDiscoveryOuter": 1.7,
    "prodCost": 600,
    "prodTimeCost": 200,
    "AttackDamageType": "Explosion",
    "ArmorClass": "HyperHeavy"
  },
  {
    "Name": "Cannon Tower",
    "power": -40,
    "sellPrice": 360,
    "healthRepairInterval": 3,
    "repairCostInterval": 3,
    "key": "Cannon Tower",
    "faction_DONTCHANGETHIS": "West_World_Alliance",
    "Health": 600,
    "MinAttackDamage": 75,
    "MaxAttackDamage": 75,
    "AttackSpeed": 3,
    "AttackSpread": 0,
    "AttackRate": 3,
    "AttackRange": 1.6,
    "detectionRange": 1.7,
    "FogDiscoveryOuter": 1.7,
    "prodCost": 600,
    "prodTimeCost": 200,
    "AttackDamageType": "Explosion",
    "ArmorClass": "HyperHeavy"
  },
  {
    "Name": "Power Pole",
    "power": 0,
    "sellPrice": 0,
    "healthRepairInterval": 0,
    "repairCostInterval": 0,
    "key": "Power Pole",
    "faction_DONTCHANGETHIS": "Neutral_Player",
    "Health": 100,
    "MinAttackDamage": 15,
    "MaxAttackDamage": 15,
    "AttackSpeed": 3,
    "AttackSpread": 0,
    "AttackRate": 0.5,
    "AttackRange": 0,
    "detectionRange": 0.6,
    "FogDiscoveryOuter": 1.35,
    "prodCost": 0,
    "prodTimeCost": 0,
    "AttackDamageType": "Normal",
    "ArmorClass": "HyperHeavy"
  },
  {
    "Name": "Machine Gun Tower",
    "power": -30,
    "sellPrice": 360,
    "healthRepairInterval": 2,
    "repairCostInterval": 3,
    "key": "Machine Gun Tower",
    "faction_DONTCHANGETHIS": "West_World_Alliance",
    "Health": 400,
    "MinAttackDamage": 15,
    "MaxAttackDamage": 15,
    "AttackSpeed": 3,
    "AttackSpread": 0,
    "AttackRate": 0.5,
    "AttackRange": 1.2,
    "detectionRange": 1.5,
    "FogDiscoveryOuter": 1.65,
    "prodCost": 600,
    "prodTimeCost": 200,
    "AttackDamageType": "Bullet",
    "ArmorClass": "HyperHeavy"
  },
  {
    "Name": "Tesla Tower",
    "power": -150,
    "sellPrice": 720,
    "healthRepairInterval": 1.33,
    "repairCostInterval": 4,
    "key": "Tesla Tower",
    "faction_DONTCHANGETHIS": "West_World_Alliance",
    "Health": 400,
    "MinAttackDamage": 50,
    "MaxAttackDamage": 500,
    "AttackSpeed": 3,
    "AttackSpread": 0,
    "AttackRate": 3,
    "AttackRange": 1.5,
    "detectionRange": 1.6,
    "FogDiscoveryOuter": 1.85,
    "prodCost": 1200,
    "prodTimeCost": 300,
    "AttackDamageType": "Electricity",
    "ArmorClass": "HyperHeavy"
  },
  {
    "Name": "Adv. Guard Tower",
    "power": -30,
    "sellPrice": 630,
    "healthRepairInterval": 1.14,
    "repairCostInterval": 3,
    "key": "Adv. Guard Tower",
    "faction_DONTCHANGETHIS": "Empire_Ascending_Order",
    "Health": 400,
    "MinAttackDamage": 600,
    "MaxAttackDamage": 700,
    "AttackSpeed": 5,
    "AttackSpread": 0,
    "AttackRate": 10,
    "AttackRange": 3,
    "detectionRange": 3.1,
    "FogDiscoveryOuter": 3.5,
    "prodCost": 1050,
    "prodTimeCost": 350,
    "AttackDamageType": "Explosion",
    "ArmorClass": "HyperHeavy"
  },
  {
    "Name": "Adv. Guard Tower",
    "power": -30,
    "sellPrice": 630,
    "healthRepairInterval": 1.14,
    "repairCostInterval": 3,
    "key": "Adv. Guard Tower",
    "faction_DONTCHANGETHIS": "West_World_Alliance",
    "Health": 400,
    "MinAttackDamage": 600,
    "MaxAttackDamage": 700,
    "AttackSpeed": 5,
    "AttackSpread": 0,
    "AttackRate": 10,
    "AttackRange": 3,
    "detectionRange": 3.1,
    "FogDiscoveryOuter": 3.5,
    "prodCost": 1050,
    "prodTimeCost": 350,
    "AttackDamageType": "Explosion",
    "ArmorClass": "HyperHeavy"
  },
  {
    "Name": "Shipyard",
    "power": -50,
    "sellPrice": 630,
    "healthRepairInterval": 2.86,
    "repairCostInterval": 3,
    "key": "Shipyard",
    "faction_DONTCHANGETHIS": "Empire_Ascending_Order",
    "Health": 1000,
    "MinAttackDamage": 15,
    "MaxAttackDamage": 15,
    "AttackSpeed": 3,
    "AttackSpread": 0,
    "AttackRate": 0.5,
    "AttackRange": 0,
    "detectionRange": 0.6,
    "FogDiscoveryOuter": 1.35,
    "prodCost": 1050,
    "prodTimeCost": 350,
    "AttackDamageType": "Normal",
    "ArmorClass": "HyperHeavy"
  },
  {
    "Name": "Shipyard",
    "power": -50,
    "sellPrice": 630,
    "healthRepairInterval": 2.86,
    "repairCostInterval": 3,
    "key": "Shipyard",
    "faction_DONTCHANGETHIS": "West_World_Alliance",
    "Health": 1000,
    "MinAttackDamage": 15,
    "MaxAttackDamage": 15,
    "AttackSpeed": 3,
    "AttackSpread": 0,
    "AttackRate": 0.5,
    "AttackRange": 0,
    "detectionRange": 0.6,
    "FogDiscoveryOuter": 1.35,
    "prodCost": 1050,
    "prodTimeCost": 350,
    "AttackDamageType": "Normal",
    "ArmorClass": "HyperHeavy"
  },
  {
    "Name": "Wood Fence",
    "power": 0,
    "sellPrice": 30,
    "healthRepairInterval": 10,
    "repairCostInterval": 50,
    "key": "Wood Fence",
    "faction_DONTCHANGETHIS": "Empire_Ascending_Order",
    "Health": 10,
    "MinAttackDamage": 15,
    "MaxAttackDamage": 15,
    "AttackSpeed": 3,
    "AttackSpread": 0,
    "AttackRate": 0.5,
    "AttackRange": 0,
    "detectionRange": 0,
    "FogDiscoveryOuter": 0.1,
    "prodCost": 50,
    "prodTimeCost": 1,
    "AttackDamageType": "Normal",
    "ArmorClass": "HyperHeavy"
  },
  {
    "Name": "Wood Fence",
    "power": 0,
    "sellPrice": 30,
    "healthRepairInterval": 10,
    "repairCostInterval": 50,
    "key": "Wood Fence",
    "faction_DONTCHANGETHIS": "West_World_Alliance",
    "Health": 10,
    "MinAttackDamage": 15,
    "MaxAttackDamage": 15,
    "AttackSpeed": 3,
    "AttackSpread": 0,
    "AttackRate": 0.5,
    "AttackRange": 0,
    "detectionRange": 0,
    "FogDiscoveryOuter": 0.1,
    "prodCost": 50,
    "prodTimeCost": 1,
    "AttackDamageType": "Normal",
    "ArmorClass": "HyperHeavy"
  },
  {
    "Name": "Watch tower long",
    "power": -20,
    "sellPrice": 180,
    "healthRepairInterval": 2,
    "repairCostInterval": 3,
    "key": "Watch tower long",
    "faction_DONTCHANGETHIS": "Empire_Ascending_Order",
    "Health": 200,
    "MinAttackDamage": 15,
    "MaxAttackDamage": 30,
    "AttackSpeed": 3,
    "AttackSpread": 0,
    "AttackRate": 0.5,
    "AttackRange": 0,
    "detectionRange": 0.6,
    "FogDiscoveryOuter": 1.35,
    "prodCost": 300,
    "prodTimeCost": 100,
    "AttackDamageType": "Bullet",
    "ArmorClass": "HyperHeavy"
  },
  {
    "Name": "Watch tower long",
    "power": -20,
    "sellPrice": 180,
    "healthRepairInterval": 2,
    "repairCostInterval": 3,
    "key": "Watch tower long",
    "faction_DONTCHANGETHIS": "West_World_Alliance",
    "Health": 200,
    "MinAttackDamage": 15,
    "MaxAttackDamage": 30,
    "AttackSpeed": 3,
    "AttackSpread": 0,
    "AttackRate": 0.5,
    "AttackRange": 0,
    "detectionRange": 0.6,
    "FogDiscoveryOuter": 1.35,
    "prodCost": 300,
    "prodTimeCost": 100,
    "AttackDamageType": "Bullet",
    "ArmorClass": "HyperHeavy"
  },
  {
    "Name": "Adv. Power Plant",
    "power": 250,
    "sellPrice": 480,
    "healthRepairInterval": 2.5,
    "repairCostInterval": 2,
    "key": "Adv. Power Plant",
    "faction_DONTCHANGETHIS": "Empire_Ascending_Order",
    "Health": 1000,
    "MinAttackDamage": 15,
    "MaxAttackDamage": 15,
    "AttackSpeed": 3,
    "AttackSpread": 0,
    "AttackRate": 0.5,
    "AttackRange": 0,
    "detectionRange": 0.6,
    "FogDiscoveryOuter": 1.35,
    "prodCost": 800,
    "prodTimeCost": 400,
    "AttackDamageType": "Normal",
    "ArmorClass": "HyperHeavy"
  },
  {
    "Name": "Adv. Power Plant",
    "power": 250,
    "sellPrice": 480,
    "healthRepairInterval": 2.5,
    "repairCostInterval": 2,
    "key": "Adv. Power Plant",
    "faction_DONTCHANGETHIS": "West_World_Alliance",
    "Health": 1000,
    "MinAttackDamage": 15,
    "MaxAttackDamage": 15,
    "AttackSpeed": 3,
    "AttackSpread": 0,
    "AttackRate": 0.5,
    "AttackRange": 0,
    "detectionRange": 0.6,
    "FogDiscoveryOuter": 1.35,
    "prodCost": 800,
    "prodTimeCost": 400,
    "AttackDamageType": "Normal",
    "ArmorClass": "HyperHeavy"
  },
  {
    "Name": "Hut",
    "power": 0,
    "sellPrice": 0,
    "healthRepairInterval": 0,
    "repairCostInterval": 0,
    "key": "Hut",
    "faction_DONTCHANGETHIS": "Neutral_Player",
    "Health": 250,
    "MinAttackDamage": 15,
    "MaxAttackDamage": 15,
    "AttackSpeed": 3,
    "AttackSpread": 0,
    "AttackRate": 0.5,
    "AttackRange": 0,
    "detectionRange": 0,
    "FogDiscoveryOuter": 1.35,
    "prodCost": 0,
    "prodTimeCost": 0,
    "AttackDamageType": "Normal",
    "ArmorClass": "HyperHeavy"
  },
  {
    "Name": "Airport",
    "power": -30,
    "sellPrice": 540,
    "healthRepairInterval": 2.22,
    "repairCostInterval": 2,
    "key": "Airport",
    "faction_DONTCHANGETHIS": "Empire_Ascending_Order",
    "Health": 1000,
    "MinAttackDamage": 15,
    "MaxAttackDamage": 15,
    "AttackSpeed": 3,
    "AttackSpread": 0,
    "AttackRate": 0.5,
    "AttackRange": 0,
    "detectionRange": 0.8625,
    "FogDiscoveryOuter": 1.35,
    "prodCost": 900,
    "prodTimeCost": 450,
    "AttackDamageType": "None",
    "ArmorClass": "HyperHeavy"
  },
  {
    "Name": "Airport",
    "power": -30,
    "sellPrice": 540,
    "healthRepairInterval": 2.22,
    "repairCostInterval": 2,
    "key": "Airport",
    "faction_DONTCHANGETHIS": "West_World_Alliance",
    "Health": 1000,
    "MinAttackDamage": 15,
    "MaxAttackDamage": 15,
    "AttackSpeed": 3,
    "AttackSpread": 0,
    "AttackRate": 0.5,
    "AttackRange": 0,
    "detectionRange": 0.8625,
    "FogDiscoveryOuter": 1.35,
    "prodCost": 900,
    "prodTimeCost": 450,
    "AttackDamageType": "None",
    "ArmorClass": "HyperHeavy"
  },
  {
    "Name": "Watch tower short",
    "power": -20,
    "sellPrice": 180,
    "healthRepairInterval": 2,
    "repairCostInterval": 3,
    "key": "Watch tower short",
    "faction_DONTCHANGETHIS": "Empire_Ascending_Order",
    "Health": 200,
    "MinAttackDamage": 15,
    "MaxAttackDamage": 30,
    "AttackSpeed": 3,
    "AttackSpread": 0,
    "AttackRate": 0.5,
    "AttackRange": 0,
    "detectionRange": 0.6,
    "FogDiscoveryOuter": 1.35,
    "prodCost": 300,
    "prodTimeCost": 100,
    "AttackDamageType": "Bullet",
    "ArmorClass": "HyperHeavy"
  },
  {
    "Name": "Watch tower short",
    "power": -20,
    "sellPrice": 180,
    "healthRepairInterval": 2,
    "repairCostInterval": 3,
    "key": "Watch tower short",
    "faction_DONTCHANGETHIS": "West_World_Alliance",
    "Health": 200,
    "MinAttackDamage": 15,
    "MaxAttackDamage": 30,
    "AttackSpeed": 3,
    "AttackSpread": 0,
    "AttackRate": 0.5,
    "AttackRange": 0,
    "detectionRange": 0.6,
    "FogDiscoveryOuter": 1.35,
    "prodCost": 300,
    "prodTimeCost": 100,
    "AttackDamageType": "Bullet",
    "ArmorClass": "HyperHeavy"
  },
  {
    "Name": "Repair Shop",
    "power": -75,
    "sellPrice": 720,
    "healthRepairInterval": 2.67,
    "repairCostInterval": 4,
    "key": "Repair Shop",
    "faction_DONTCHANGETHIS": "Empire_Ascending_Order",
    "Health": 800,
    "MinAttackDamage": 15,
    "MaxAttackDamage": 15,
    "AttackSpeed": 3,
    "AttackSpread": 0,
    "AttackRate": 0.5,
    "AttackRange": 0,
    "detectionRange": 0.6,
    "FogDiscoveryOuter": 1.35,
    "prodCost": 1200,
    "prodTimeCost": 300,
    "AttackDamageType": "Normal",
    "ArmorClass": "HyperHeavy"
  },
  {
    "Name": "Repair Shop",
    "power": -75,
    "sellPrice": 720,
    "healthRepairInterval": 2.67,
    "repairCostInterval": 4,
    "key": "Repair Shop",
    "faction_DONTCHANGETHIS": "West_World_Alliance",
    "Health": 800,
    "MinAttackDamage": 15,
    "MaxAttackDamage": 15,
    "AttackSpeed": 3,
    "AttackSpread": 0,
    "AttackRate": 0.5,
    "AttackRange": 0,
    "detectionRange": 0.6,
    "FogDiscoveryOuter": 1.35,
    "prodCost": 1200,
    "prodTimeCost": 300,
    "AttackDamageType": "Normal",
    "ArmorClass": "HyperHeavy"
  },
  {
    "Name": "Laboratory",
    "power": -250,
    "sellPrice": 1800,
    "healthRepairInterval": 1,
    "repairCostInterval": 3,
    "key": "Laboratory",
    "faction_DONTCHANGETHIS": "Empire_Ascending_Order",
    "Health": 1000,
    "MinAttackDamage": 15,
    "MaxAttackDamage": 15,
    "AttackSpeed": 3,
    "AttackSpread": 0,
    "AttackRate": 0.5,
    "AttackRange": 0,
    "detectionRange": 0.6,
    "FogDiscoveryOuter": 1.35,
    "prodCost": 3000,
    "prodTimeCost": 1000,
    "AttackDamageType": "Normal",
    "ArmorClass": "HyperHeavy"
  },
  {
    "Name": "Laboratory",
    "power": -250,
    "sellPrice": 1800,
    "healthRepairInterval": 1,
    "repairCostInterval": 3,
    "key": "Laboratory",
    "faction_DONTCHANGETHIS": "West_World_Alliance",
    "Health": 1000,
    "MinAttackDamage": 15,
    "MaxAttackDamage": 15,
    "AttackSpeed": 3,
    "AttackSpread": 0,
    "AttackRate": 0.5,
    "AttackRange": 0,
    "detectionRange": 0.6,
    "FogDiscoveryOuter": 1.35,
    "prodCost": 3000,
    "prodTimeCost": 1000,
    "AttackDamageType": "Normal",
    "ArmorClass": "HyperHeavy"
  },
  {
    "Name": "Gas Tank",
    "power": 0,
    "sellPrice": 0,
    "healthRepairInterval": 0,
    "repairCostInterval": 0,
    "key": "Gas Tank",
    "faction_DONTCHANGETHIS": "Neutral_Player",
    "Health": 600,
    "MinAttackDamage": 15,
    "MaxAttackDamage": 15,
    "AttackSpeed": 3,
    "AttackSpread": 0,
    "AttackRate": 0.5,
    "AttackRange": 0,
    "detectionRange": 0.72,
    "FogDiscoveryOuter": 1.35,
    "prodCost": 0,
    "prodTimeCost": 0,
    "AttackDamageType": "Normal",
    "ArmorClass": "HyperHeavy"
  },
  {
    "Name": "Heliport",
    "power": -60,
    "sellPrice": 900,
    "healthRepairInterval": 2.67,
    "repairCostInterval": 5,
    "key": "Heliport",
    "faction_DONTCHANGETHIS": "Empire_Ascending_Order",
    "Health": 800,
    "MinAttackDamage": 15,
    "MaxAttackDamage": 15,
    "AttackSpeed": 3,
    "AttackSpread": 0,
    "AttackRate": 0.5,
    "AttackRange": 0,
    "detectionRange": 0.6,
    "FogDiscoveryOuter": 1.35,
    "prodCost": 1500,
    "prodTimeCost": 300,
    "AttackDamageType": "Normal",
    "ArmorClass": "HyperHeavy"
  },
  {
    "Name": "Heliport",
    "power": -60,
    "sellPrice": 900,
    "healthRepairInterval": 2.67,
    "repairCostInterval": 5,
    "key": "Heliport",
    "faction_DONTCHANGETHIS": "West_World_Alliance",
    "Health": 800,
    "MinAttackDamage": 15,
    "MaxAttackDamage": 15,
    "AttackSpeed": 3,
    "AttackSpread": 0,
    "AttackRate": 0.5,
    "AttackRange": 0,
    "detectionRange": 0.6,
    "FogDiscoveryOuter": 1.35,
    "prodCost": 1500,
    "prodTimeCost": 300,
    "AttackDamageType": "Normal",
    "ArmorClass": "HyperHeavy"
  },
  {
    "Name": "BigBuilding",
    "power": 0,
    "sellPrice": 7200,
    "healthRepairInterval": 16.67,
    "repairCostInterval": 20,
    "key": "BigBuilding",
    "faction_DONTCHANGETHIS": "Empire_Ascending_Order",
    "Health": 10000,
    "MinAttackDamage": 15,
    "MaxAttackDamage": 15,
    "AttackSpeed": 3,
    "AttackSpread": 0,
    "AttackRate": 0.5,
    "AttackRange": 0,
    "detectionRange": 0.6,
    "FogDiscoveryOuter": 2,
    "prodCost": 12000,
    "prodTimeCost": 600,
    "AttackDamageType": "Normal",
    "ArmorClass": "HyperHeavy"
  },
  {
    "Name": "BigBuilding",
    "power": 0,
    "sellPrice": 0,
    "healthRepairInterval": 0,
    "repairCostInterval": 0,
    "key": "BigBuilding",
    "faction_DONTCHANGETHIS": "West_World_Alliance",
    "Health": 10000,
    "MinAttackDamage": 15,
    "MaxAttackDamage": 15,
    "AttackSpeed": 3,
    "AttackSpread": 0,
    "AttackRate": 0.5,
    "AttackRange": 0,
    "detectionRange": 0.6,
    "FogDiscoveryOuter": 2,
    "prodCost": 0,
    "prodTimeCost": 0,
    "AttackDamageType": "Normal",
    "ArmorClass": "HyperHeavy"
  },
  {
    "Name": "Ubik\u2019s Hand",
    "power": -150,
    "sellPrice": 840,
    "healthRepairInterval": 2.86,
    "repairCostInterval": 4,
    "key": "Ubik\u2019s Hand",
    "faction_DONTCHANGETHIS": "Empire_Ascending_Order",
    "Health": 1000,
    "MinAttackDamage": 150,
    "MaxAttackDamage": 150,
    "AttackSpeed": 3,
    "AttackSpread": 0,
    "AttackRate": 1,
    "AttackRange": 1.6,
    "detectionRange": 1.7,
    "FogDiscoveryOuter": 1.85,
    "prodCost": 1400,
    "prodTimeCost": 350,
    "AttackDamageType": "Laser",
    "ArmorClass": "HyperHeavy"
  },
  {
    "Name": "Wheels",
    "power": 0,
    "sellPrice": 30,
    "healthRepairInterval": 10,
    "repairCostInterval": 50,
    "key": "Wheels",
    "faction_DONTCHANGETHIS": "Empire_Ascending_Order",
    "Health": 10,
    "MinAttackDamage": 15,
    "MaxAttackDamage": 15,
    "AttackSpeed": 3,
    "AttackSpread": 0,
    "AttackRate": 0.5,
    "AttackRange": 0,
    "detectionRange": 0,
    "FogDiscoveryOuter": 0.1,
    "prodCost": 50,
    "prodTimeCost": 1,
    "AttackDamageType": "Normal",
    "ArmorClass": "HyperHeavy"
  },
  {
    "Name": "Wheels",
    "power": 0,
    "sellPrice": 30,
    "healthRepairInterval": 10,
    "repairCostInterval": 50,
    "key": "Wheels",
    "faction_DONTCHANGETHIS": "West_World_Alliance",
    "Health": 10,
    "MinAttackDamage": 15,
    "MaxAttackDamage": 15,
    "AttackSpeed": 3,
    "AttackSpread": 0,
    "AttackRate": 0.5,
    "AttackRange": 0,
    "detectionRange": 0,
    "FogDiscoveryOuter": 0.1,
    "prodCost": 50,
    "prodTimeCost": 1,
    "AttackDamageType": "Normal",
    "ArmorClass": "HyperHeavy"
  },
  {
    "Name": "Power Generator",
    "power": -30,
    "sellPrice": 0,
    "healthRepairInterval": 0,
    "repairCostInterval": 0,
    "key": "Power Generator",
    "faction_DONTCHANGETHIS": "Neutral_Player",
    "Health": 750,
    "MinAttackDamage": 15,
    "MaxAttackDamage": 15,
    "AttackSpeed": 3,
    "AttackSpread": 0,
    "AttackRate": 0.5,
    "AttackRange": 0,
    "detectionRange": 0,
    "FogDiscoveryOuter": 1.35,
    "prodCost": 0,
    "prodTimeCost": 0,
    "AttackDamageType": "Normal",
    "ArmorClass": "HyperHeavy"
  },
  {
    "Name": "Satellite Dish",
    "power": 0,
    "sellPrice": 0,
    "healthRepairInterval": 0,
    "repairCostInterval": 0,
    "key": "Satellite Dish",
    "faction_DONTCHANGETHIS": "Neutral_Player",
    "Health": 60,
    "MinAttackDamage": 15,
    "MaxAttackDamage": 15,
    "AttackSpeed": 3,
    "AttackSpread": 0,
    "AttackRate": 0.5,
    "AttackRange": 0,
    "detectionRange": 0.54,
    "FogDiscoveryOuter": 1.35,
    "prodCost": 0,
    "prodTimeCost": 0,
    "AttackDamageType": "Normal",
    "ArmorClass": "HyperHeavy"
  },
  {
    "Name": "Robot Arm",
    "power": 0,
    "sellPrice": 0,
    "healthRepairInterval": 0,
    "repairCostInterval": 0,
    "key": "Robot Arm",
    "faction_DONTCHANGETHIS": "Neutral_Player",
    "Health": 100,
    "MinAttackDamage": 15,
    "MaxAttackDamage": 15,
    "AttackSpeed": 3,
    "AttackSpread": 0,
    "AttackRate": 0.5,
    "AttackRange": 0,
    "detectionRange": 0.6,
    "FogDiscoveryOuter": 1.35,
    "prodCost": 0,
    "prodTimeCost": 0,
    "AttackDamageType": "Normal",
    "ArmorClass": "HyperHeavy"
  },
  {
    "Name": "Tent",
    "power": 0,
    "sellPrice": 0,
    "healthRepairInterval": 0,
    "repairCostInterval": 0,
    "key": "Tent",
    "faction_DONTCHANGETHIS": "Neutral_Player",
    "Health": 100,
    "MinAttackDamage": 15,
    "MaxAttackDamage": 15,
    "AttackSpeed": 3,
    "AttackSpread": 0,
    "AttackRate": 0.5,
    "AttackRange": 0,
    "detectionRange": 0.8625,
    "FogDiscoveryOuter": 1.35,
    "prodCost": 0,
    "prodTimeCost": 0,
    "AttackDamageType": "Normal",
    "ArmorClass": "Medium"
  },
  {
    "Name": "Bunker",
    "power": -20,
    "sellPrice": 180,
    "healthRepairInterval": 6,
    "repairCostInterval": 3,
    "key": "Bunker",
    "faction_DONTCHANGETHIS": "Empire_Ascending_Order",
    "Health": 600,
    "MinAttackDamage": 15,
    "MaxAttackDamage": 15,
    "AttackSpeed": 3,
    "AttackSpread": 0,
    "AttackRate": 0.5,
    "AttackRange": 1,
    "detectionRange": 1.2,
    "FogDiscoveryOuter": 1.8,
    "prodCost": 300,
    "prodTimeCost": 100,
    "AttackDamageType": "Bullet",
    "ArmorClass": "HyperHeavy"
  },
  {
    "Name": "Brainquarter",
    "power": -100,
    "sellPrice": 1800,
    "healthRepairInterval": 1.6,
    "repairCostInterval": 4,
    "key": "Brainquarter",
    "faction_DONTCHANGETHIS": "Empire_Ascending_Order",
    "Health": 1200,
    "MinAttackDamage": 15,
    "MaxAttackDamage": 15,
    "AttackSpeed": 3,
    "AttackSpread": 0,
    "AttackRate": 0.5,
    "AttackRange": 0,
    "detectionRange": 0.8625,
    "FogDiscoveryOuter": 1.35,
    "prodCost": 3000,
    "prodTimeCost": 750,
    "AttackDamageType": "Normal",
    "ArmorClass": "HyperHeavy"
  },
  {
    "Name": "Gap Generator",
    "power": -20,
    "sellPrice": 840,
    "healthRepairInterval": 1.14,
    "repairCostInterval": 4,
    "key": "Gap Generator",
    "faction_DONTCHANGETHIS": "West_World_Alliance",
    "Health": 400,
    "MinAttackDamage": 15,
    "MaxAttackDamage": 15,
    "AttackSpeed": 3,
    "AttackSpread": 0,
    "AttackRate": 0.5,
    "AttackRange": 0.6,
    "detectionRange": 0.6,
    "FogDiscoveryOuter": 1.35,
    "prodCost": 1400,
    "prodTimeCost": 350,
    "AttackDamageType": "Normal",
    "ArmorClass": "HyperHeavy"
  },
  {
    "Name": "Kennel",
    "power": -10,
    "sellPrice": 120,
    "healthRepairInterval": 100,
    "repairCostInterval": 50,
    "key": "Kennel",
    "faction_DONTCHANGETHIS": "Empire_Ascending_Order",
    "Health": 400,
    "MinAttackDamage": 15,
    "MaxAttackDamage": 15,
    "AttackSpeed": 3,
    "AttackSpread": 0,
    "AttackRate": 0.5,
    "AttackRange": 0,
    "detectionRange": 0.6,
    "FogDiscoveryOuter": 1.35,
    "prodCost": 200,
    "prodTimeCost": 4,
    "AttackDamageType": "Normal",
    "ArmorClass": "HyperHeavy"
  },
  {
    "Name": "Kennel",
    "power": -10,
    "sellPrice": 120,
    "healthRepairInterval": 100,
    "repairCostInterval": 50,
    "key": "Kennel",
    "faction_DONTCHANGETHIS": "West_World_Alliance",
    "Health": 400,
    "MinAttackDamage": 15,
    "MaxAttackDamage": 15,
    "AttackSpeed": 3,
    "AttackSpread": 0,
    "AttackRate": 0.5,
    "AttackRange": 0,
    "detectionRange": 0.6,
    "FogDiscoveryOuter": 1.35,
    "prodCost": 200,
    "prodTimeCost": 4,
    "AttackDamageType": "Normal",
    "ArmorClass": "HyperHeavy"
  },
  {
    "Name": "Supermap Exit",
    "power": 0,
    "sellPrice": 0,
    "healthRepairInterval": 0,
    "repairCostInterval": 0,
    "key": "Supermap Exit",
    "faction_DONTCHANGETHIS": "Neutral_Player",
    "Health": 1,
    "MinAttackDamage": 15,
    "MaxAttackDamage": 15,
    "AttackSpeed": 3,
    "AttackSpread": 0,
    "AttackRate": 0.5,
    "AttackRange": 0,
    "detectionRange": 0.8625,
    "FogDiscoveryOuter": 1.35,
    "prodCost": 0,
    "prodTimeCost": 0,
    "AttackDamageType": "Normal",
    "ArmorClass": "HyperHeavy"
  }
]